energysim/ParameterSweep.py
energysim/__init__.py
energysim/csAdapter.py
energysim/csv_adapter.py
energysim/external_simulator.py
energysim/meAdapter.py
energysim/ppAdapter.py
energysim/pyScriptAdapter.py
energysim/pypsaAdapter.py
energysim/signalAdapter.py
energysim/utils.py
energysim-2.1.9.1.dist-info/LICENSE
energysim-2.1.9.1.dist-info/METADATA
energysim-2.1.9.1.dist-info/WHEEL
energysim-2.1.9.1.dist-info/top_level.txt
energysim-2.1.9.1.dist-info/RECORD
