Metadata-Version: 2.1
Name: energysim
Version: 2.1.9.1
Summary: Python package for cosimulation of multi-energy systems
Home-page: https://github.com/dgusain1/energysim
Author: Digvijay Gusain
Author-email: digvijay.gusain29@gmail.com
License: MIT
Platform: UNKNOWN
Classifier: License :: OSI Approved :: MIT License
Classifier: Programming Language :: Python :: 3
Classifier: Programming Language :: Python :: 3.6
Requires-Dist: numpy
Requires-Dist: pandas
Requires-Dist: tqdm
Requires-Dist: fmpy (==0.2.14)
Requires-Dist: pandapower
Requires-Dist: pypsa
Requires-Dist: networkx
Requires-Dist: matplotlib
Requires-Dist: tables
Requires-Dist: h5py
